pylib/__init__.py
pylib/compare.py
pylib/configs.py
pylib/dates.py
pylib/dicts.py
pylib/files.py
pylib/filters.py
pylib/gitrepos.py
pylib/htmlparser.py
pylib/inputs.py
pylib/logs.py
pylib/macos.py
pylib/mvnutil.py
pylib/opts.py
pylib/output.py
pylib/patterns.py
pylib/procs.py
pylib/runners.py
pylib/stash.py
pylib/stash_types.py
pylib/strconverters.py
pylib/templates.py
pylib/terminals.py
pylib/timing.py
pylib/xmlparser.py
lt_pylib-0.0.2.dist-info/LICENSE
lt_pylib-0.0.2.dist-info/METADATA
lt_pylib-0.0.2.dist-info/WHEEL
lt_pylib-0.0.2.dist-info/top_level.txt
lt_pylib-0.0.2.dist-info/RECORD
